trafaret/__init__.py
trafaret/async_mixins.py
trafaret/base.py
trafaret/codes.py
trafaret/constructor.py
trafaret/dataerror.py
trafaret/internet.py
trafaret/keys.py
trafaret/lib.py
trafaret/numeric.py
trafaret/regexp.py
trafaret/utils.py
trafaret/contrib/__init__.py
trafaret/contrib/object_id.py
trafaret/contrib/rfc_3339.py
trafaret-2.1.1.dist-info/LICENSE.txt
trafaret-2.1.1.dist-info/METADATA
trafaret-2.1.1.dist-info/WHEEL
trafaret-2.1.1.dist-info/top_level.txt
trafaret-2.1.1.dist-info/RECORD
