Metadata-Version: 2.1
Name: trafaret
Version: 2.1.1
Summary: Validation and parsing library
Home-page: https://github.com/Deepwalker/trafaret/
Author: Barbuza, Deepwalker, nimnull
Author-email: krivushinme@gmail.com
License: BSD
Keywords: validation form forms data schema
Platform: UNKNOWN
Classifier: Intended Audience :: Developers
Classifier: License :: OSI Approved :: BSD License
Classifier: Operating System :: OS Independent
Classifier: Programming Language :: Python
Classifier: Programming Language :: Python :: 3
Provides-Extra: objectid
Provides-Extra: rfc3339
